__init__.py
cli.py
graphing.py
parsing.py
printing.py
pprint_problems-0.1.17.dist-info/LICENSE
pprint_problems-0.1.17.dist-info/METADATA
pprint_problems-0.1.17.dist-info/WHEEL
pprint_problems-0.1.17.dist-info/entry_points.txt
pprint_problems-0.1.17.dist-info/top_level.txt
pprint_problems-0.1.17.dist-info/RECORD
