Metadata-Version: 2.2
Name: pprint_problems
Version: 0.1.17
Summary: Used to print entries from jsonl files, developed with LLM evals in mind.
Author-email: Andrew Keenan Richardson <richardson.andrew@gmail.com>
Project-URL: Homepage, https://github.com/qemqemqem/pprint_problems
Classifier: Programming Language :: Python :: 3
Classifier: License :: OSI Approved :: MIT License
Classifier: Operating System :: OS Independent
Requires-Python: >=3.9
License-File: LICENSE
Requires-Dist: matplotlib>=3.5.1
Requires-Dist: numpy>=1.21.5
Requires-Dist: rich>=13.9.4
Requires-Dist: scipy>=1.8.0
Requires-Dist: Pillow>=10.0.0
Requires-Dist: kiwisolver>=1.4.0
Requires-Dist: cycler>=0.10.0
